{
  "status": "UP",
  "response_time": 0.3555312156677246,
  "extra_info": null,
  "stable_count": 60,
  "degraded_count": 0,
  "alert_mode": false,
  "last_check_timestamp_utc": "2025-11-26T00:38:33.936740Z",
  "recent_response_times": [
    0.3305337429046631,
    0.29474377632141113,
    0.3555312156677246
  ],
  "history": [
    {
      "timestamp": "2025-11-25T15:40:43.850426Z",
      "status": "UP",
      "response_time": 0.289,
      "extra_info": null
    },
    {
      "timestamp": "2025-11-25T15:50:19.938838Z",
      "status": "UP",
      "response_time": 0.351,
      "extra_info": null
    },
    {
      "timestamp": "2025-11-25T15:58:07.189559Z",
      "status": "UP",
      "response_time": 0.378,
      "extra_info": null
    },
    {
      "timestamp": "2025-11-25T16:10:34.790942Z",
      "status": "UP",
      "response_time": 0.301,
      "extra_info": null
    },
    {
      "timestamp": "2025-11-25T16:25:05.962705Z",
      "status": "UP",
      "response_time": 0.13,
      "extra_info": null
    },
    {
      "timestamp": "2025-11-25T16:41:15.592900Z",
      "status": "UP",
      "response_time": 0.379,
      "extra_info": null
    },
    {
      "timestamp": "2025-11-25T16:53:52.927458Z",
      "status": "UP",
      "response_time": 0.37,
      "extra_info": null
    },
    {
      "timestamp": "2025-11-25T17:03:29.026383Z",
      "status": "UP",
      "response_time": 0.125,
      "extra_info": null
    },
    {
      "timestamp": "2025-11-25T17:14:59.780715Z",
      "status": "UP",
      "response_time": 0.212,
      "extra_info": null
    },
    {
      "timestamp": "2025-11-25T17:28:48.763935Z",
      "status": "UP",
      "response_time": 0.372,
      "extra_info": null
    },
    {
      "timestamp": "2025-11-25T17:39:31.922579Z",
      "status": "UP",
      "response_time": 0.236,
      "extra_info": null
    },
    {
      "timestamp": "2025-11-25T17:48:06.345801Z",
      "status": "UP",
      "response_time": 0.329,
      "extra_info": null
    },
    {
      "timestamp": "2025-11-25T17:55:32.647630Z",
      "status": "UP",
      "response_time": 0.129,
      "extra_info": null
    },
    {
      "timestamp": "2025-11-25T18:08:13.645788Z",
      "status": "UP",
      "response_time": 0.323,
      "extra_info": null
    },
    {
      "timestamp": "2025-11-25T18:22:03.842972Z",
      "status": "UP",
      "response_time": 0.306,
      "extra_info": null
    },
    {
      "timestamp": "2025-11-25T18:40:18.273896Z",
      "status": "UP",
      "response_time": 0.316,
      "extra_info": null
    },
    {
      "timestamp": "2025-11-25T18:51:47.681732Z",
      "status": "UP",
      "response_time": 0.268,
      "extra_info": null
    },
    {
      "timestamp": "2025-11-25T18:59:32.006110Z",
      "status": "UP",
      "response_time": 0.127,
      "extra_info": null
    },
    {
      "timestamp": "2025-11-25T19:09:58.490362Z",
      "status": "UP",
      "response_time": 0.214,
      "extra_info": null
    },
    {
      "timestamp": "2025-11-25T19:22:26.582072Z",
      "status": "UP",
      "response_time": 0.147,
      "extra_info": null
    },
    {
      "timestamp": "2025-11-25T19:31:33.806542Z",
      "status": "UP",
      "response_time": 0.377,
      "extra_info": null
    },
    {
      "timestamp": "2025-11-25T19:40:08.041792Z",
      "status": "UP",
      "response_time": 0.186,
      "extra_info": null
    },
    {
      "timestamp": "2025-11-25T19:47:45.831425Z",
      "status": "UP",
      "response_time": 0.269,
      "extra_info": null
    },
    {
      "timestamp": "2025-11-25T19:55:18.312302Z",
      "status": "UP",
      "response_time": 0.128,
      "extra_info": null
    },
    {
      "timestamp": "2025-11-25T20:05:23.354943Z",
      "status": "UP",
      "response_time": 0.318,
      "extra_info": null
    },
    {
      "timestamp": "2025-11-25T20:17:37.248366Z",
      "status": "UP",
      "response_time": 0.374,
      "extra_info": null
    },
    {
      "timestamp": "2025-11-25T20:32:34.750259Z",
      "status": "UP",
      "response_time": 0.331,
      "extra_info": null
    },
    {
      "timestamp": "2025-11-25T20:42:47.049342Z",
      "status": "UP",
      "response_time": 0.419,
      "extra_info": null
    },
    {
      "timestamp": "2025-11-25T20:51:20.856605Z",
      "status": "UP",
      "response_time": 0.458,
      "extra_info": null
    },
    {
      "timestamp": "2025-11-25T20:58:43.325828Z",
      "status": "UP",
      "response_time": 0.381,
      "extra_info": null
    },
    {
      "timestamp": "2025-11-25T21:08:58.261337Z",
      "status": "UP",
      "response_time": 0.242,
      "extra_info": null
    },
    {
      "timestamp": "2025-11-25T21:21:46.808019Z",
      "status": "UP",
      "response_time": 0.366,
      "extra_info": null
    },
    {
      "timestamp": "2025-11-25T21:31:47.685009Z",
      "status": "UP",
      "response_time": 0.268,
      "extra_info": null
    },
    {
      "timestamp": "2025-11-25T21:40:35.486130Z",
      "status": "UP",
      "response_time": 0.136,
      "extra_info": null
    },
    {
      "timestamp": "2025-11-25T21:47:52.635415Z",
      "status": "UP",
      "response_time": 0.41,
      "extra_info": null
    },
    {
      "timestamp": "2025-11-25T21:55:18.950359Z",
      "status": "UP",
      "response_time": 0.332,
      "extra_info": null
    },
    {
      "timestamp": "2025-11-25T22:04:55.820825Z",
      "status": "UP",
      "response_time": 0.35,
      "extra_info": null
    },
    {
      "timestamp": "2025-11-25T22:16:50.809515Z",
      "status": "UP",
      "response_time": 0.333,
      "extra_info": null
    },
    {
      "timestamp": "2025-11-25T22:30:44.184881Z",
      "status": "UP",
      "response_time": 0.284,
      "extra_info": null
    },
    {
      "timestamp": "2025-11-25T22:40:45.956733Z",
      "status": "UP",
      "response_time": 0.241,
      "extra_info": null
    },
    {
      "timestamp": "2025-11-25T22:48:49.141948Z",
      "status": "UP",
      "response_time": 0.267,
      "extra_info": null
    },
    {
      "timestamp": "2025-11-25T22:56:23.728082Z",
      "status": "UP",
      "response_time": 0.288,
      "extra_info": null
    },
    {
      "timestamp": "2025-11-25T23:06:57.985507Z",
      "status": "UP",
      "response_time": 0.374,
      "extra_info": null
    },
    {
      "timestamp": "2025-11-25T23:18:56.099431Z",
      "status": "UP",
      "response_time": 0.488,
      "extra_info": null
    },
    {
      "timestamp": "2025-11-25T23:29:42.127958Z",
      "status": "UP",
      "response_time": 0.24,
      "extra_info": null
    },
    {
      "timestamp": "2025-11-25T23:38:30.440431Z",
      "status": "UP",
      "response_time": 0.125,
      "extra_info": null
    },
    {
      "timestamp": "2025-11-25T23:45:59.377902Z",
      "status": "UP",
      "response_time": 0.226,
      "extra_info": null
    },
    {
      "timestamp": "2025-11-25T23:53:37.956833Z",
      "status": "UP",
      "response_time": 0.331,
      "extra_info": null
    },
    {
      "timestamp": "2025-11-26T00:07:15.097032Z",
      "status": "UP",
      "response_time": 0.295,
      "extra_info": null
    },
    {
      "timestamp": "2025-11-26T00:38:33.936740Z",
      "status": "UP",
      "response_time": 0.356,
      "extra_info": null
    }
  ]
}