{
  "status": "UP",
  "response_time": 0.3801875114440918,
  "extra_info": null,
  "stable_count": 2377,
  "degraded_count": 0,
  "alert_mode": false,
  "last_check_timestamp_utc": "2026-05-17T14:42:41.016566Z",
  "recent_response_times": [
    0.27600598335266113,
    0.11198019981384277,
    0.3801875114440918
  ],
  "history": [
    {
      "timestamp": "2026-05-16T11:30:47.577696Z",
      "status": "UP",
      "response_time": 0.346,
      "extra_info": null
    },
    {
      "timestamp": "2026-05-16T11:54:05.415914Z",
      "status": "UP",
      "response_time": 0.131,
      "extra_info": null
    },
    {
      "timestamp": "2026-05-16T12:18:41.689316Z",
      "status": "UP",
      "response_time": 0.198,
      "extra_info": null
    },
    {
      "timestamp": "2026-05-16T12:44:23.000376Z",
      "status": "UP",
      "response_time": 0.329,
      "extra_info": null
    },
    {
      "timestamp": "2026-05-16T13:15:39.178062Z",
      "status": "UP",
      "response_time": 0.349,
      "extra_info": null
    },
    {
      "timestamp": "2026-05-16T13:56:26.470614Z",
      "status": "UP",
      "response_time": 0.13,
      "extra_info": null
    },
    {
      "timestamp": "2026-05-16T14:32:57.807658Z",
      "status": "UP",
      "response_time": 0.272,
      "extra_info": null
    },
    {
      "timestamp": "2026-05-16T14:57:40.477780Z",
      "status": "UP",
      "response_time": 0.13,
      "extra_info": null
    },
    {
      "timestamp": "2026-05-16T15:28:19.828451Z",
      "status": "UP",
      "response_time": 0.396,
      "extra_info": null
    },
    {
      "timestamp": "2026-05-16T15:52:14.535381Z",
      "status": "UP",
      "response_time": 0.123,
      "extra_info": null
    },
    {
      "timestamp": "2026-05-16T16:14:04.394830Z",
      "status": "UP",
      "response_time": 0.108,
      "extra_info": null
    },
    {
      "timestamp": "2026-05-16T16:36:58.881987Z",
      "status": "UP",
      "response_time": 0.249,
      "extra_info": null
    },
    {
      "timestamp": "2026-05-16T17:03:08.553483Z",
      "status": "UP",
      "response_time": 0.129,
      "extra_info": null
    },
    {
      "timestamp": "2026-05-16T17:29:02.770045Z",
      "status": "UP",
      "response_time": 0.263,
      "extra_info": null
    },
    {
      "timestamp": "2026-05-16T17:53:17.966230Z",
      "status": "UP",
      "response_time": 0.205,
      "extra_info": null
    },
    {
      "timestamp": "2026-05-16T18:14:16.946539Z",
      "status": "UP",
      "response_time": 0.453,
      "extra_info": null
    },
    {
      "timestamp": "2026-05-16T18:38:27.721668Z",
      "status": "UP",
      "response_time": 0.477,
      "extra_info": null
    },
    {
      "timestamp": "2026-05-16T19:06:02.126500Z",
      "status": "UP",
      "response_time": 0.312,
      "extra_info": null
    },
    {
      "timestamp": "2026-05-16T19:36:03.380215Z",
      "status": "UP",
      "response_time": 0.131,
      "extra_info": null
    },
    {
      "timestamp": "2026-05-16T20:02:04.959876Z",
      "status": "UP",
      "response_time": 0.35,
      "extra_info": null
    },
    {
      "timestamp": "2026-05-16T20:23:28.356462Z",
      "status": "UP",
      "response_time": 0.218,
      "extra_info": null
    },
    {
      "timestamp": "2026-05-16T20:44:01.327273Z",
      "status": "UP",
      "response_time": 0.253,
      "extra_info": null
    },
    {
      "timestamp": "2026-05-16T21:05:44.367828Z",
      "status": "UP",
      "response_time": 0.338,
      "extra_info": null
    },
    {
      "timestamp": "2026-05-16T21:28:50.537802Z",
      "status": "UP",
      "response_time": 0.112,
      "extra_info": null
    },
    {
      "timestamp": "2026-05-16T21:51:28.252718Z",
      "status": "UP",
      "response_time": 0.107,
      "extra_info": null
    },
    {
      "timestamp": "2026-05-16T22:10:33.040289Z",
      "status": "UP",
      "response_time": 0.453,
      "extra_info": null
    },
    {
      "timestamp": "2026-05-16T22:30:14.233140Z",
      "status": "UP",
      "response_time": 0.352,
      "extra_info": null
    },
    {
      "timestamp": "2026-05-16T22:52:57.377358Z",
      "status": "UP",
      "response_time": 0.427,
      "extra_info": null
    },
    {
      "timestamp": "2026-05-16T23:13:49.410732Z",
      "status": "UP",
      "response_time": 0.394,
      "extra_info": null
    },
    {
      "timestamp": "2026-05-16T23:35:36.263310Z",
      "status": "UP",
      "response_time": 0.393,
      "extra_info": null
    },
    {
      "timestamp": "2026-05-17T00:00:13.744846Z",
      "status": "UP",
      "response_time": 0.128,
      "extra_info": null
    },
    {
      "timestamp": "2026-05-17T01:13:04.922246Z",
      "status": "UP",
      "response_time": 0.327,
      "extra_info": null
    },
    {
      "timestamp": "2026-05-17T02:00:36.234117Z",
      "status": "UP",
      "response_time": 0.398,
      "extra_info": null
    },
    {
      "timestamp": "2026-05-17T03:19:47.625545Z",
      "status": "UP",
      "response_time": 0.125,
      "extra_info": null
    },
    {
      "timestamp": "2026-05-17T04:43:08.750383Z",
      "status": "UP",
      "response_time": 0.342,
      "extra_info": null
    },
    {
      "timestamp": "2026-05-17T05:59:22.639622Z",
      "status": "UP",
      "response_time": 0.179,
      "extra_info": null
    },
    {
      "timestamp": "2026-05-17T07:10:50.681368Z",
      "status": "UP",
      "response_time": 0.348,
      "extra_info": null
    },
    {
      "timestamp": "2026-05-17T08:01:06.452244Z",
      "status": "UP",
      "response_time": 0.4,
      "extra_info": null
    },
    {
      "timestamp": "2026-05-17T08:52:37.129364Z",
      "status": "UP",
      "response_time": 0.418,
      "extra_info": null
    },
    {
      "timestamp": "2026-05-17T09:28:46.877179Z",
      "status": "UP",
      "response_time": 0.207,
      "extra_info": null
    },
    {
      "timestamp": "2026-05-17T10:06:49.992924Z",
      "status": "UP",
      "response_time": 0.401,
      "extra_info": null
    },
    {
      "timestamp": "2026-05-17T10:40:01.759538Z",
      "status": "UP",
      "response_time": 0.538,
      "extra_info": null
    },
    {
      "timestamp": "2026-05-17T11:08:18.053087Z",
      "status": "UP",
      "response_time": 0.122,
      "extra_info": null
    },
    {
      "timestamp": "2026-05-17T11:36:58.411494Z",
      "status": "UP",
      "response_time": 0.433,
      "extra_info": null
    },
    {
      "timestamp": "2026-05-17T12:02:28.313294Z",
      "status": "UP",
      "response_time": 0.173,
      "extra_info": null
    },
    {
      "timestamp": "2026-05-17T12:33:33.589068Z",
      "status": "UP",
      "response_time": 0.367,
      "extra_info": null
    },
    {
      "timestamp": "2026-05-17T13:00:32.696996Z",
      "status": "UP",
      "response_time": 0.176,
      "extra_info": null
    },
    {
      "timestamp": "2026-05-17T13:38:49.640816Z",
      "status": "UP",
      "response_time": 0.276,
      "extra_info": null
    },
    {
      "timestamp": "2026-05-17T14:12:56.298225Z",
      "status": "UP",
      "response_time": 0.112,
      "extra_info": null
    },
    {
      "timestamp": "2026-05-17T14:42:41.016566Z",
      "status": "UP",
      "response_time": 0.38,
      "extra_info": null
    }
  ]
}