{
  "status": "UP",
  "response_time": 0.22901463508605957,
  "extra_info": null,
  "stable_count": 3893,
  "degraded_count": 0,
  "alert_mode": false,
  "last_check_timestamp_utc": "2025-07-12T19:14:43.320371Z",
  "recent_response_times": [
    0.3360133171081543,
    0.14223670959472656,
    0.22901463508605957
  ],
  "history": [
    {
      "timestamp": "2025-07-12T03:13:48.355006Z",
      "status": "UP",
      "response_time": 0.231,
      "extra_info": null
    },
    {
      "timestamp": "2025-07-12T04:02:10.638252Z",
      "status": "UP",
      "response_time": 0.339,
      "extra_info": null
    },
    {
      "timestamp": "2025-07-12T04:39:04.086169Z",
      "status": "UP",
      "response_time": 0.195,
      "extra_info": null
    },
    {
      "timestamp": "2025-07-12T04:56:39.931900Z",
      "status": "UP",
      "response_time": 0.457,
      "extra_info": null
    },
    {
      "timestamp": "2025-07-12T05:21:58.580645Z",
      "status": "UP",
      "response_time": 0.374,
      "extra_info": null
    },
    {
      "timestamp": "2025-07-12T05:41:30.644176Z",
      "status": "UP",
      "response_time": 0.34,
      "extra_info": null
    },
    {
      "timestamp": "2025-07-12T05:52:21.029295Z",
      "status": "UP",
      "response_time": 0.291,
      "extra_info": null
    },
    {
      "timestamp": "2025-07-12T06:16:28.888139Z",
      "status": "UP",
      "response_time": 0.38,
      "extra_info": null
    },
    {
      "timestamp": "2025-07-12T06:46:05.761358Z",
      "status": "UP",
      "response_time": 0.202,
      "extra_info": null
    },
    {
      "timestamp": "2025-07-12T06:59:45.295425Z",
      "status": "UP",
      "response_time": 0.395,
      "extra_info": null
    },
    {
      "timestamp": "2025-07-12T07:25:43.842885Z",
      "status": "UP",
      "response_time": 0.342,
      "extra_info": null
    },
    {
      "timestamp": "2025-07-12T07:40:20.506637Z",
      "status": "UP",
      "response_time": 0.24,
      "extra_info": null
    },
    {
      "timestamp": "2025-07-12T07:49:59.205803Z",
      "status": "UP",
      "response_time": 0.352,
      "extra_info": null
    },
    {
      "timestamp": "2025-07-12T07:59:51.658784Z",
      "status": "UP",
      "response_time": 0.28,
      "extra_info": null
    },
    {
      "timestamp": "2025-07-12T08:32:49.506914Z",
      "status": "UP",
      "response_time": 0.377,
      "extra_info": null
    },
    {
      "timestamp": "2025-07-12T08:50:44.187047Z",
      "status": "UP",
      "response_time": 0.303,
      "extra_info": null
    },
    {
      "timestamp": "2025-07-12T09:00:30.306079Z",
      "status": "UP",
      "response_time": 0.234,
      "extra_info": null
    },
    {
      "timestamp": "2025-07-12T09:27:37.093077Z",
      "status": "UP",
      "response_time": 0.27,
      "extra_info": null
    },
    {
      "timestamp": "2025-07-12T09:42:14.417272Z",
      "status": "UP",
      "response_time": 0.382,
      "extra_info": null
    },
    {
      "timestamp": "2025-07-12T09:52:00.393845Z",
      "status": "UP",
      "response_time": 0.219,
      "extra_info": null
    },
    {
      "timestamp": "2025-07-12T10:10:53.492332Z",
      "status": "UP",
      "response_time": 0.306,
      "extra_info": null
    },
    {
      "timestamp": "2025-07-12T10:36:12.596062Z",
      "status": "UP",
      "response_time": 0.459,
      "extra_info": null
    },
    {
      "timestamp": "2025-07-12T10:49:42.280727Z",
      "status": "UP",
      "response_time": 0.361,
      "extra_info": null
    },
    {
      "timestamp": "2025-07-12T10:59:26.188069Z",
      "status": "UP",
      "response_time": 0.271,
      "extra_info": null
    },
    {
      "timestamp": "2025-07-12T11:22:40.974714Z",
      "status": "UP",
      "response_time": 0.347,
      "extra_info": null
    },
    {
      "timestamp": "2025-07-12T11:35:49.741996Z",
      "status": "UP",
      "response_time": 0.121,
      "extra_info": null
    },
    {
      "timestamp": "2025-07-12T11:46:15.925499Z",
      "status": "UP",
      "response_time": 0.307,
      "extra_info": null
    },
    {
      "timestamp": "2025-07-12T11:55:46.884983Z",
      "status": "UP",
      "response_time": 0.166,
      "extra_info": null
    },
    {
      "timestamp": "2025-07-12T12:37:53.702256Z",
      "status": "UP",
      "response_time": 0.371,
      "extra_info": null
    },
    {
      "timestamp": "2025-07-12T13:15:03.811225Z",
      "status": "UP",
      "response_time": 0.256,
      "extra_info": null
    },
    {
      "timestamp": "2025-07-12T13:40:33.609057Z",
      "status": "UP",
      "response_time": 0.225,
      "extra_info": null
    },
    {
      "timestamp": "2025-07-12T13:52:51.056898Z",
      "status": "UP",
      "response_time": 0.328,
      "extra_info": null
    },
    {
      "timestamp": "2025-07-12T14:11:43.243538Z",
      "status": "UP",
      "response_time": 0.287,
      "extra_info": null
    },
    {
      "timestamp": "2025-07-12T14:33:45.366291Z",
      "status": "UP",
      "response_time": 0.261,
      "extra_info": null
    },
    {
      "timestamp": "2025-07-12T14:47:07.404434Z",
      "status": "UP",
      "response_time": 0.23,
      "extra_info": null
    },
    {
      "timestamp": "2025-07-12T14:56:51.199040Z",
      "status": "UP",
      "response_time": 0.326,
      "extra_info": null
    },
    {
      "timestamp": "2025-07-12T15:21:59.292205Z",
      "status": "UP",
      "response_time": 0.18,
      "extra_info": null
    },
    {
      "timestamp": "2025-07-12T15:38:42.593864Z",
      "status": "UP",
      "response_time": 0.214,
      "extra_info": null
    },
    {
      "timestamp": "2025-07-12T15:50:36.361849Z",
      "status": "UP",
      "response_time": 0.321,
      "extra_info": null
    },
    {
      "timestamp": "2025-07-12T16:00:07.421644Z",
      "status": "UP",
      "response_time": 0.133,
      "extra_info": null
    },
    {
      "timestamp": "2025-07-12T16:32:51.502521Z",
      "status": "UP",
      "response_time": 0.335,
      "extra_info": null
    },
    {
      "timestamp": "2025-07-12T16:50:32.379344Z",
      "status": "UP",
      "response_time": 0.248,
      "extra_info": null
    },
    {
      "timestamp": "2025-07-12T17:00:09.493343Z",
      "status": "UP",
      "response_time": 0.177,
      "extra_info": null
    },
    {
      "timestamp": "2025-07-12T17:23:55.344359Z",
      "status": "UP",
      "response_time": 0.243,
      "extra_info": null
    },
    {
      "timestamp": "2025-07-12T17:40:14.884216Z",
      "status": "UP",
      "response_time": 0.214,
      "extra_info": null
    },
    {
      "timestamp": "2025-07-12T17:50:55.790448Z",
      "status": "UP",
      "response_time": 0.365,
      "extra_info": null
    },
    {
      "timestamp": "2025-07-12T18:11:06.532017Z",
      "status": "UP",
      "response_time": 0.174,
      "extra_info": null
    },
    {
      "timestamp": "2025-07-12T18:41:49.813435Z",
      "status": "UP",
      "response_time": 0.336,
      "extra_info": null
    },
    {
      "timestamp": "2025-07-12T18:55:35.324304Z",
      "status": "UP",
      "response_time": 0.142,
      "extra_info": null
    },
    {
      "timestamp": "2025-07-12T19:14:43.320371Z",
      "status": "UP",
      "response_time": 0.229,
      "extra_info": null
    }
  ]
}