{
  "status": "UP",
  "response_time": 0.3512120246887207,
  "extra_info": null,
  "stable_count": 1032,
  "degraded_count": 0,
  "alert_mode": false,
  "last_check_timestamp_utc": "2025-05-31T01:47:14.514891Z",
  "recent_response_times": [
    0.09864568710327148,
    0.34279704093933105,
    0.3512120246887207
  ],
  "history": [
    {
      "timestamp": "2025-05-30T10:37:02.056768Z",
      "status": "UP",
      "response_time": 0.292,
      "extra_info": null
    },
    {
      "timestamp": "2025-05-30T10:49:58.297672Z",
      "status": "UP",
      "response_time": 0.346,
      "extra_info": null
    },
    {
      "timestamp": "2025-05-30T10:59:49.497684Z",
      "status": "UP",
      "response_time": 0.591,
      "extra_info": null
    },
    {
      "timestamp": "2025-05-30T11:21:48.157119Z",
      "status": "UP",
      "response_time": 0.453,
      "extra_info": null
    },
    {
      "timestamp": "2025-05-30T11:32:43.583937Z",
      "status": "UP",
      "response_time": 0.343,
      "extra_info": null
    },
    {
      "timestamp": "2025-05-30T11:42:30.375677Z",
      "status": "UP",
      "response_time": 0.337,
      "extra_info": null
    },
    {
      "timestamp": "2025-05-30T11:52:28.850375Z",
      "status": "UP",
      "response_time": 0.527,
      "extra_info": null
    },
    {
      "timestamp": "2025-05-30T12:22:11.652817Z",
      "status": "UP",
      "response_time": 0.545,
      "extra_info": null
    },
    {
      "timestamp": "2025-05-30T13:03:52.361018Z",
      "status": "UP",
      "response_time": 0.358,
      "extra_info": null
    },
    {
      "timestamp": "2025-05-30T13:37:08.282337Z",
      "status": "UP",
      "response_time": 0.53,
      "extra_info": null
    },
    {
      "timestamp": "2025-05-30T13:50:25.050568Z",
      "status": "UP",
      "response_time": 0.325,
      "extra_info": null
    },
    {
      "timestamp": "2025-05-30T14:00:01.194759Z",
      "status": "UP",
      "response_time": 0.437,
      "extra_info": null
    },
    {
      "timestamp": "2025-05-30T14:27:36.581148Z",
      "status": "UP",
      "response_time": 0.698,
      "extra_info": null
    },
    {
      "timestamp": "2025-05-30T14:44:54.110476Z",
      "status": "UP",
      "response_time": 0.16,
      "extra_info": null
    },
    {
      "timestamp": "2025-05-30T14:54:50.439634Z",
      "status": "UP",
      "response_time": 0.549,
      "extra_info": null
    },
    {
      "timestamp": "2025-05-30T15:17:48.549203Z",
      "status": "UP",
      "response_time": 0.509,
      "extra_info": null
    },
    {
      "timestamp": "2025-05-30T15:36:46.235635Z",
      "status": "UP",
      "response_time": 0.399,
      "extra_info": null
    },
    {
      "timestamp": "2025-05-30T15:47:59.529221Z",
      "status": "UP",
      "response_time": 0.534,
      "extra_info": null
    },
    {
      "timestamp": "2025-05-30T15:57:58.228173Z",
      "status": "UP",
      "response_time": 0.101,
      "extra_info": null
    },
    {
      "timestamp": "2025-05-30T16:31:04.642203Z",
      "status": "UP",
      "response_time": 0.481,
      "extra_info": null
    },
    {
      "timestamp": "2025-05-30T16:50:33.465024Z",
      "status": "UP",
      "response_time": 0.157,
      "extra_info": null
    },
    {
      "timestamp": "2025-05-30T17:00:19.883062Z",
      "status": "UP",
      "response_time": 0.462,
      "extra_info": null
    },
    {
      "timestamp": "2025-05-30T17:24:37.637054Z",
      "status": "UP",
      "response_time": 0.42,
      "extra_info": null
    },
    {
      "timestamp": "2025-05-30T17:39:35.218291Z",
      "status": "UP",
      "response_time": 0.334,
      "extra_info": null
    },
    {
      "timestamp": "2025-05-30T17:49:23.845276Z",
      "status": "UP",
      "response_time": 0.306,
      "extra_info": null
    },
    {
      "timestamp": "2025-05-30T17:58:59.577108Z",
      "status": "UP",
      "response_time": 0.335,
      "extra_info": null
    },
    {
      "timestamp": "2025-05-30T18:36:03.212950Z",
      "status": "UP",
      "response_time": 0.307,
      "extra_info": null
    },
    {
      "timestamp": "2025-05-30T18:52:15.820638Z",
      "status": "UP",
      "response_time": 0.129,
      "extra_info": null
    },
    {
      "timestamp": "2025-05-30T19:09:08.088306Z",
      "status": "UP",
      "response_time": 0.114,
      "extra_info": null
    },
    {
      "timestamp": "2025-05-30T19:24:30.655300Z",
      "status": "UP",
      "response_time": 0.479,
      "extra_info": null
    },
    {
      "timestamp": "2025-05-30T19:35:48.508405Z",
      "status": "UP",
      "response_time": 0.482,
      "extra_info": null
    },
    {
      "timestamp": "2025-05-30T19:45:28.657355Z",
      "status": "UP",
      "response_time": 0.305,
      "extra_info": null
    },
    {
      "timestamp": "2025-05-30T19:55:03.868128Z",
      "status": "UP",
      "response_time": 0.357,
      "extra_info": null
    },
    {
      "timestamp": "2025-05-30T20:19:13.779033Z",
      "status": "UP",
      "response_time": 0.264,
      "extra_info": null
    },
    {
      "timestamp": "2025-05-30T20:37:51.490147Z",
      "status": "UP",
      "response_time": 0.244,
      "extra_info": null
    },
    {
      "timestamp": "2025-05-30T20:50:11.735034Z",
      "status": "UP",
      "response_time": 0.324,
      "extra_info": null
    },
    {
      "timestamp": "2025-05-30T20:59:58.487006Z",
      "status": "UP",
      "response_time": 0.258,
      "extra_info": null
    },
    {
      "timestamp": "2025-05-30T21:24:05.528778Z",
      "status": "UP",
      "response_time": 0.389,
      "extra_info": null
    },
    {
      "timestamp": "2025-05-30T21:36:26.844973Z",
      "status": "UP",
      "response_time": 0.114,
      "extra_info": null
    },
    {
      "timestamp": "2025-05-30T21:45:58.827263Z",
      "status": "UP",
      "response_time": 0.43,
      "extra_info": null
    },
    {
      "timestamp": "2025-05-30T21:55:42.138067Z",
      "status": "UP",
      "response_time": 0.284,
      "extra_info": null
    },
    {
      "timestamp": "2025-05-30T22:17:49.097069Z",
      "status": "UP",
      "response_time": 0.241,
      "extra_info": null
    },
    {
      "timestamp": "2025-05-30T22:38:03.547273Z",
      "status": "UP",
      "response_time": 0.451,
      "extra_info": null
    },
    {
      "timestamp": "2025-05-30T22:48:59.693154Z",
      "status": "UP",
      "response_time": 0.317,
      "extra_info": null
    },
    {
      "timestamp": "2025-05-30T22:58:44.769649Z",
      "status": "UP",
      "response_time": 0.283,
      "extra_info": null
    },
    {
      "timestamp": "2025-05-30T23:24:03.089210Z",
      "status": "UP",
      "response_time": 0.319,
      "extra_info": null
    },
    {
      "timestamp": "2025-05-30T23:37:18.930456Z",
      "status": "UP",
      "response_time": 0.11,
      "extra_info": null
    },
    {
      "timestamp": "2025-05-30T23:47:07.688090Z",
      "status": "UP",
      "response_time": 0.099,
      "extra_info": null
    },
    {
      "timestamp": "2025-05-30T23:56:54.925604Z",
      "status": "UP",
      "response_time": 0.343,
      "extra_info": null
    },
    {
      "timestamp": "2025-05-31T01:47:14.514891Z",
      "status": "UP",
      "response_time": 0.351,
      "extra_info": null
    }
  ]
}