{
  "status": "UP",
  "response_time": 0.24435663223266602,
  "extra_info": null,
  "stable_count": 2247,
  "degraded_count": 0,
  "alert_mode": false,
  "last_check_timestamp_utc": "2025-06-18T05:40:19.503112Z",
  "recent_response_times": [
    0.1536095142364502,
    0.277484655380249,
    0.24435663223266602
  ],
  "history": [
    {
      "timestamp": "2025-06-17T10:55:29.428211Z",
      "status": "UP",
      "response_time": 0.29,
      "extra_info": null
    },
    {
      "timestamp": "2025-06-17T11:16:15.700747Z",
      "status": "UP",
      "response_time": 0.331,
      "extra_info": null
    },
    {
      "timestamp": "2025-06-17T11:31:03.397543Z",
      "status": "UP",
      "response_time": 0.364,
      "extra_info": null
    },
    {
      "timestamp": "2025-06-17T11:42:53.102748Z",
      "status": "UP",
      "response_time": 0.191,
      "extra_info": null
    },
    {
      "timestamp": "2025-06-17T11:52:47.491395Z",
      "status": "UP",
      "response_time": 0.377,
      "extra_info": null
    },
    {
      "timestamp": "2025-06-17T12:26:27.540388Z",
      "status": "UP",
      "response_time": 0.301,
      "extra_info": null
    },
    {
      "timestamp": "2025-06-17T13:09:04.312569Z",
      "status": "UP",
      "response_time": 0.266,
      "extra_info": null
    },
    {
      "timestamp": "2025-06-17T13:43:34.436557Z",
      "status": "UP",
      "response_time": 0.329,
      "extra_info": null
    },
    {
      "timestamp": "2025-06-17T13:56:23.964201Z",
      "status": "UP",
      "response_time": 0.285,
      "extra_info": null
    },
    {
      "timestamp": "2025-06-17T14:21:27.595139Z",
      "status": "UP",
      "response_time": 0.161,
      "extra_info": null
    },
    {
      "timestamp": "2025-06-17T14:43:06.532942Z",
      "status": "UP",
      "response_time": 0.15,
      "extra_info": null
    },
    {
      "timestamp": "2025-06-17T14:55:11.023155Z",
      "status": "UP",
      "response_time": 0.234,
      "extra_info": null
    },
    {
      "timestamp": "2025-06-17T15:19:50.289744Z",
      "status": "UP",
      "response_time": 0.277,
      "extra_info": null
    },
    {
      "timestamp": "2025-06-17T15:40:20.514009Z",
      "status": "UP",
      "response_time": 0.391,
      "extra_info": null
    },
    {
      "timestamp": "2025-06-17T15:52:34.273489Z",
      "status": "UP",
      "response_time": 0.1,
      "extra_info": null
    },
    {
      "timestamp": "2025-06-17T16:15:29.445332Z",
      "status": "UP",
      "response_time": 0.227,
      "extra_info": null
    },
    {
      "timestamp": "2025-06-17T16:46:08.551295Z",
      "status": "UP",
      "response_time": 0.317,
      "extra_info": null
    },
    {
      "timestamp": "2025-06-17T17:00:27.641027Z",
      "status": "UP",
      "response_time": 0.305,
      "extra_info": null
    },
    {
      "timestamp": "2025-06-17T17:26:08.070265Z",
      "status": "UP",
      "response_time": 0.311,
      "extra_info": null
    },
    {
      "timestamp": "2025-06-17T17:42:43.430952Z",
      "status": "UP",
      "response_time": 0.108,
      "extra_info": null
    },
    {
      "timestamp": "2025-06-17T17:52:43.945560Z",
      "status": "UP",
      "response_time": 0.245,
      "extra_info": null
    },
    {
      "timestamp": "2025-06-17T18:17:38.213054Z",
      "status": "UP",
      "response_time": 0.349,
      "extra_info": null
    },
    {
      "timestamp": "2025-06-17T18:45:55.158146Z",
      "status": "UP",
      "response_time": 0.335,
      "extra_info": null
    },
    {
      "timestamp": "2025-06-17T18:58:44.501902Z",
      "status": "UP",
      "response_time": 0.112,
      "extra_info": null
    },
    {
      "timestamp": "2025-06-17T19:21:05.956054Z",
      "status": "UP",
      "response_time": 0.276,
      "extra_info": null
    },
    {
      "timestamp": "2025-06-17T19:32:38.558774Z",
      "status": "UP",
      "response_time": 0.331,
      "extra_info": null
    },
    {
      "timestamp": "2025-06-17T19:50:23.910978Z",
      "status": "UP",
      "response_time": 0.285,
      "extra_info": null
    },
    {
      "timestamp": "2025-06-17T20:00:18.124637Z",
      "status": "UP",
      "response_time": 0.233,
      "extra_info": null
    },
    {
      "timestamp": "2025-06-17T20:29:33.096338Z",
      "status": "UP",
      "response_time": 0.302,
      "extra_info": null
    },
    {
      "timestamp": "2025-06-17T20:45:06.106484Z",
      "status": "UP",
      "response_time": 0.212,
      "extra_info": null
    },
    {
      "timestamp": "2025-06-17T20:55:03.908894Z",
      "status": "UP",
      "response_time": 0.275,
      "extra_info": null
    },
    {
      "timestamp": "2025-06-17T21:17:03.422307Z",
      "status": "UP",
      "response_time": 0.325,
      "extra_info": null
    },
    {
      "timestamp": "2025-06-17T21:34:01.285945Z",
      "status": "UP",
      "response_time": 0.263,
      "extra_info": null
    },
    {
      "timestamp": "2025-06-17T21:46:57.004951Z",
      "status": "UP",
      "response_time": 0.332,
      "extra_info": null
    },
    {
      "timestamp": "2025-06-17T21:56:54.544300Z",
      "status": "UP",
      "response_time": 0.238,
      "extra_info": null
    },
    {
      "timestamp": "2025-06-17T22:20:29.519272Z",
      "status": "UP",
      "response_time": 0.325,
      "extra_info": null
    },
    {
      "timestamp": "2025-06-17T22:39:45.925335Z",
      "status": "UP",
      "response_time": 0.346,
      "extra_info": null
    },
    {
      "timestamp": "2025-06-17T22:50:43.959980Z",
      "status": "UP",
      "response_time": 0.3,
      "extra_info": null
    },
    {
      "timestamp": "2025-06-17T23:00:40.673015Z",
      "status": "UP",
      "response_time": 0.333,
      "extra_info": null
    },
    {
      "timestamp": "2025-06-17T23:25:32.042110Z",
      "status": "UP",
      "response_time": 0.111,
      "extra_info": null
    },
    {
      "timestamp": "2025-06-17T23:40:01.141376Z",
      "status": "UP",
      "response_time": 0.371,
      "extra_info": null
    },
    {
      "timestamp": "2025-06-17T23:49:48.189925Z",
      "status": "UP",
      "response_time": 0.304,
      "extra_info": null
    },
    {
      "timestamp": "2025-06-17T23:59:27.997635Z",
      "status": "UP",
      "response_time": 0.285,
      "extra_info": null
    },
    {
      "timestamp": "2025-06-18T02:09:39.813783Z",
      "status": "UP",
      "response_time": 0.334,
      "extra_info": null
    },
    {
      "timestamp": "2025-06-18T03:29:54.203860Z",
      "status": "UP",
      "response_time": 0.408,
      "extra_info": null
    },
    {
      "timestamp": "2025-06-18T04:02:07.968068Z",
      "status": "UP",
      "response_time": 0.391,
      "extra_info": null
    },
    {
      "timestamp": "2025-06-18T04:37:17.738775Z",
      "status": "UP",
      "response_time": 0.365,
      "extra_info": null
    },
    {
      "timestamp": "2025-06-18T04:55:39.834170Z",
      "status": "UP",
      "response_time": 0.154,
      "extra_info": null
    },
    {
      "timestamp": "2025-06-18T05:19:14.364536Z",
      "status": "UP",
      "response_time": 0.277,
      "extra_info": null
    },
    {
      "timestamp": "2025-06-18T05:40:19.503112Z",
      "status": "UP",
      "response_time": 0.244,
      "extra_info": null
    }
  ]
}