{
  "status": "UP",
  "response_time": 0.2550992965698242,
  "extra_info": null,
  "stable_count": 9,
  "degraded_count": 0,
  "alert_mode": false,
  "last_check_timestamp_utc": "2025-04-21T03:57:17.967286Z",
  "recent_response_times": [
    0.3992297649383545,
    0.4268913269042969,
    0.2550992965698242
  ],
  "history": [
    {
      "timestamp": "2025-04-20T12:40:07.171490Z",
      "status": "UP",
      "response_time": 0.326,
      "extra_info": null
    },
    {
      "timestamp": "2025-04-20T13:05:34.660271Z",
      "status": "UP",
      "response_time": 0.346,
      "extra_info": null
    },
    {
      "timestamp": "2025-04-20T13:31:48.440988Z",
      "status": "UP",
      "response_time": 0.415,
      "extra_info": null
    },
    {
      "timestamp": "2025-04-20T13:44:09.299825Z",
      "status": "UP",
      "response_time": 0.454,
      "extra_info": null
    },
    {
      "timestamp": "2025-04-20T13:53:56.378421Z",
      "status": "UP",
      "response_time": 0.166,
      "extra_info": null
    },
    {
      "timestamp": "2025-04-20T14:12:22.565734Z",
      "status": "UP",
      "response_time": 0.422,
      "extra_info": null
    },
    {
      "timestamp": "2025-04-20T14:31:48.295301Z",
      "status": "UP",
      "response_time": 0.462,
      "extra_info": null
    },
    {
      "timestamp": "2025-04-20T14:43:38.996203Z",
      "status": "UP",
      "response_time": 0.216,
      "extra_info": null
    },
    {
      "timestamp": "2025-04-20T14:53:11.346507Z",
      "status": "UP",
      "response_time": 0.399,
      "extra_info": null
    },
    {
      "timestamp": "2025-04-20T15:11:34.004697Z",
      "status": "UP",
      "response_time": 0.393,
      "extra_info": null
    },
    {
      "timestamp": "2025-04-20T15:29:20.636647Z",
      "status": "UP",
      "response_time": 0.339,
      "extra_info": null
    },
    {
      "timestamp": "2025-04-20T15:42:04.662711Z",
      "status": "UP",
      "response_time": 0.541,
      "extra_info": null
    },
    {
      "timestamp": "2025-04-20T15:51:50.527427Z",
      "status": "UP",
      "response_time": 0.446,
      "extra_info": null
    },
    {
      "timestamp": "2025-04-20T16:10:49.465270Z",
      "status": "UP",
      "response_time": 0.119,
      "extra_info": null
    },
    {
      "timestamp": "2025-04-20T16:34:48.443127Z",
      "status": "UP",
      "response_time": 0.419,
      "extra_info": null
    },
    {
      "timestamp": "2025-04-20T16:47:51.205128Z",
      "status": "UP",
      "response_time": 0.242,
      "extra_info": null
    },
    {
      "timestamp": "2025-04-20T16:57:33.610495Z",
      "status": "UP",
      "response_time": 0.498,
      "extra_info": null
    },
    {
      "timestamp": "2025-04-20T17:19:25.642929Z",
      "status": "UP",
      "response_time": 0.44,
      "extra_info": null
    },
    {
      "timestamp": "2025-04-20T17:33:51.220185Z",
      "status": "UP",
      "response_time": 0.478,
      "extra_info": null
    },
    {
      "timestamp": "2025-04-20T17:43:56.687991Z",
      "status": "UP",
      "response_time": 0.515,
      "extra_info": null
    },
    {
      "timestamp": "2025-04-20T17:53:43.903765Z",
      "status": "UP",
      "response_time": 0.435,
      "extra_info": null
    },
    {
      "timestamp": "2025-04-20T18:17:36.156207Z",
      "status": "UP",
      "response_time": 0.388,
      "extra_info": null
    },
    {
      "timestamp": "2025-04-20T18:40:23.028346Z",
      "status": "UP",
      "response_time": 0.291,
      "extra_info": null
    },
    {
      "timestamp": "2025-04-20T18:52:00.150931Z",
      "status": "UP",
      "response_time": 0.314,
      "extra_info": null
    },
    {
      "timestamp": "2025-04-20T19:08:54.169393Z",
      "status": "UP",
      "response_time": 0.129,
      "extra_info": null
    },
    {
      "timestamp": "2025-04-20T19:23:15.988725Z",
      "status": "UP",
      "response_time": 0.36,
      "extra_info": null
    },
    {
      "timestamp": "2025-04-20T19:34:12.608969Z",
      "status": "UP",
      "response_time": 0.142,
      "extra_info": null
    },
    {
      "timestamp": "2025-04-20T19:44:04.811829Z",
      "status": "UP",
      "response_time": 0.351,
      "extra_info": null
    },
    {
      "timestamp": "2025-04-20T19:53:38.342107Z",
      "status": "UP",
      "response_time": 0.165,
      "extra_info": null
    },
    {
      "timestamp": "2025-04-20T20:14:05.278309Z",
      "status": "UP",
      "response_time": 0.463,
      "extra_info": null
    },
    {
      "timestamp": "2025-04-20T20:31:15.365575Z",
      "status": "UP",
      "response_time": 0.458,
      "extra_info": null
    },
    {
      "timestamp": "2025-04-20T20:43:06.564160Z",
      "status": "UP",
      "response_time": 0.314,
      "extra_info": null
    },
    {
      "timestamp": "2025-04-20T20:52:54.150634Z",
      "status": "UP",
      "response_time": 0.356,
      "extra_info": null
    },
    {
      "timestamp": "2025-04-20T21:10:27.919850Z",
      "status": "UP",
      "response_time": 0.404,
      "extra_info": null
    },
    {
      "timestamp": "2025-04-20T21:26:56.666305Z",
      "status": "UP",
      "response_time": 0.284,
      "extra_info": null
    },
    {
      "timestamp": "2025-04-20T21:38:47.076368Z",
      "status": "UP",
      "response_time": 0.411,
      "extra_info": null
    },
    {
      "timestamp": "2025-04-20T21:48:34.168603Z",
      "status": "UP",
      "response_time": 0.175,
      "extra_info": null
    },
    {
      "timestamp": "2025-04-20T21:58:23.338654Z",
      "status": "UP",
      "response_time": 0.417,
      "extra_info": null
    },
    {
      "timestamp": "2025-04-20T22:23:49.965090Z",
      "status": "UP",
      "response_time": 0.349,
      "extra_info": null
    },
    {
      "timestamp": "2025-04-20T22:39:12.512714Z",
      "status": "UP",
      "response_time": 0.404,
      "extra_info": null
    },
    {
      "timestamp": "2025-04-20T22:49:01.271488Z",
      "status": "ERROR",
      "response_time": 0.387,
      "extra_info": "Status code: 403"
    },
    {
      "timestamp": "2025-04-20T22:58:33.201802Z",
      "status": "UP",
      "response_time": 0.193,
      "extra_info": null
    },
    {
      "timestamp": "2025-04-20T23:22:14.738684Z",
      "status": "UP",
      "response_time": 0.414,
      "extra_info": null
    },
    {
      "timestamp": "2025-04-20T23:33:47.176041Z",
      "status": "UP",
      "response_time": 0.331,
      "extra_info": null
    },
    {
      "timestamp": "2025-04-20T23:43:33.950529Z",
      "status": "UP",
      "response_time": 0.439,
      "extra_info": null
    },
    {
      "timestamp": "2025-04-20T23:53:14.960051Z",
      "status": "UP",
      "response_time": 0.341,
      "extra_info": null
    },
    {
      "timestamp": "2025-04-21T01:06:08.555736Z",
      "status": "UP",
      "response_time": 0.119,
      "extra_info": null
    },
    {
      "timestamp": "2025-04-21T02:47:47.568152Z",
      "status": "UP",
      "response_time": 0.399,
      "extra_info": null
    },
    {
      "timestamp": "2025-04-21T03:32:25.677492Z",
      "status": "UP",
      "response_time": 0.427,
      "extra_info": null
    },
    {
      "timestamp": "2025-04-21T03:57:17.967286Z",
      "status": "UP",
      "response_time": 0.255,
      "extra_info": null
    }
  ]
}