{
  "status": "UP",
  "response_time": 0.4138295650482178,
  "extra_info": null,
  "stable_count": 129,
  "degraded_count": 0,
  "alert_mode": false,
  "last_check_timestamp_utc": "2025-04-25T15:51:04.375331Z",
  "recent_response_times": [
    0.12277483940124512,
    0.37584376335144043,
    0.4138295650482178
  ],
  "history": [
    {
      "timestamp": "2025-04-24T22:56:36.009440Z",
      "status": "UP",
      "response_time": 0.424,
      "extra_info": null
    },
    {
      "timestamp": "2025-04-24T23:19:15.322513Z",
      "status": "UP",
      "response_time": 0.414,
      "extra_info": null
    },
    {
      "timestamp": "2025-04-24T23:31:41.110251Z",
      "status": "UP",
      "response_time": 0.332,
      "extra_info": null
    },
    {
      "timestamp": "2025-04-24T23:43:56.854838Z",
      "status": "UP",
      "response_time": 0.362,
      "extra_info": null
    },
    {
      "timestamp": "2025-04-24T23:53:49.543418Z",
      "status": "UP",
      "response_time": 0.402,
      "extra_info": null
    },
    {
      "timestamp": "2025-04-25T01:09:46.453537Z",
      "status": "UP",
      "response_time": 0.303,
      "extra_info": null
    },
    {
      "timestamp": "2025-04-25T02:44:54.150113Z",
      "status": "UP",
      "response_time": 0.176,
      "extra_info": null
    },
    {
      "timestamp": "2025-04-25T03:28:39.776432Z",
      "status": "UP",
      "response_time": 0.458,
      "extra_info": null
    },
    {
      "timestamp": "2025-04-25T03:52:04.192307Z",
      "status": "UP",
      "response_time": 0.462,
      "extra_info": null
    },
    {
      "timestamp": "2025-04-25T04:12:48.002089Z",
      "status": "UP",
      "response_time": 0.433,
      "extra_info": null
    },
    {
      "timestamp": "2025-04-25T04:36:16.096749Z",
      "status": "UP",
      "response_time": 0.361,
      "extra_info": null
    },
    {
      "timestamp": "2025-04-25T04:50:33.226562Z",
      "status": "UP",
      "response_time": 0.401,
      "extra_info": null
    },
    {
      "timestamp": "2025-04-25T05:00:19.798013Z",
      "status": "UP",
      "response_time": 0.503,
      "extra_info": null
    },
    {
      "timestamp": "2025-04-25T05:26:40.030198Z",
      "status": "UP",
      "response_time": 0.407,
      "extra_info": null
    },
    {
      "timestamp": "2025-04-25T05:41:25.339793Z",
      "status": "UP",
      "response_time": 0.314,
      "extra_info": null
    },
    {
      "timestamp": "2025-04-25T05:51:18.745821Z",
      "status": "UP",
      "response_time": 0.315,
      "extra_info": null
    },
    {
      "timestamp": "2025-04-25T06:13:19.499095Z",
      "status": "UP",
      "response_time": 0.477,
      "extra_info": null
    },
    {
      "timestamp": "2025-04-25T06:43:00.022486Z",
      "status": "UP",
      "response_time": 0.129,
      "extra_info": null
    },
    {
      "timestamp": "2025-04-25T06:55:22.323139Z",
      "status": "UP",
      "response_time": 0.313,
      "extra_info": null
    },
    {
      "timestamp": "2025-04-25T07:17:26.691317Z",
      "status": "UP",
      "response_time": 0.391,
      "extra_info": null
    },
    {
      "timestamp": "2025-04-25T07:31:22.817858Z",
      "status": "UP",
      "response_time": 0.42,
      "extra_info": null
    },
    {
      "timestamp": "2025-04-25T07:41:46.653840Z",
      "status": "UP",
      "response_time": 0.471,
      "extra_info": null
    },
    {
      "timestamp": "2025-04-25T07:51:46.101468Z",
      "status": "UP",
      "response_time": 0.351,
      "extra_info": null
    },
    {
      "timestamp": "2025-04-25T08:14:13.488005Z",
      "status": "UP",
      "response_time": 0.454,
      "extra_info": null
    },
    {
      "timestamp": "2025-04-25T08:40:38.735722Z",
      "status": "UP",
      "response_time": 0.288,
      "extra_info": null
    },
    {
      "timestamp": "2025-04-25T08:55:38.881323Z",
      "status": "UP",
      "response_time": 0.496,
      "extra_info": null
    },
    {
      "timestamp": "2025-04-25T09:19:10.771468Z",
      "status": "UP",
      "response_time": 0.543,
      "extra_info": null
    },
    {
      "timestamp": "2025-04-25T09:35:40.869117Z",
      "status": "UP",
      "response_time": 0.301,
      "extra_info": null
    },
    {
      "timestamp": "2025-04-25T09:45:46.987554Z",
      "status": "UP",
      "response_time": 0.235,
      "extra_info": null
    },
    {
      "timestamp": "2025-04-25T09:55:28.646800Z",
      "status": "UP",
      "response_time": 0.335,
      "extra_info": null
    },
    {
      "timestamp": "2025-04-25T10:18:59.866358Z",
      "status": "UP",
      "response_time": 0.374,
      "extra_info": null
    },
    {
      "timestamp": "2025-04-25T10:40:00.272595Z",
      "status": "UP",
      "response_time": 0.418,
      "extra_info": null
    },
    {
      "timestamp": "2025-04-25T10:50:19.993777Z",
      "status": "UP",
      "response_time": 0.478,
      "extra_info": null
    },
    {
      "timestamp": "2025-04-25T11:00:08.209600Z",
      "status": "UP",
      "response_time": 0.183,
      "extra_info": null
    },
    {
      "timestamp": "2025-04-25T11:21:17.754601Z",
      "status": "UP",
      "response_time": 0.336,
      "extra_info": null
    },
    {
      "timestamp": "2025-04-25T11:32:29.269364Z",
      "status": "UP",
      "response_time": 0.415,
      "extra_info": null
    },
    {
      "timestamp": "2025-04-25T11:42:17.691235Z",
      "status": "UP",
      "response_time": 0.438,
      "extra_info": null
    },
    {
      "timestamp": "2025-04-25T11:52:05.100566Z",
      "status": "UP",
      "response_time": 0.465,
      "extra_info": null
    },
    {
      "timestamp": "2025-04-25T12:19:56.104096Z",
      "status": "UP",
      "response_time": 0.131,
      "extra_info": null
    },
    {
      "timestamp": "2025-04-25T12:59:29.804541Z",
      "status": "UP",
      "response_time": 0.341,
      "extra_info": null
    },
    {
      "timestamp": "2025-04-25T13:32:54.781231Z",
      "status": "UP",
      "response_time": 0.416,
      "extra_info": null
    },
    {
      "timestamp": "2025-04-25T13:46:34.012730Z",
      "status": "UP",
      "response_time": 0.419,
      "extra_info": null
    },
    {
      "timestamp": "2025-04-25T13:56:16.895327Z",
      "status": "UP",
      "response_time": 0.43,
      "extra_info": null
    },
    {
      "timestamp": "2025-04-25T14:18:39.634961Z",
      "status": "UP",
      "response_time": 0.257,
      "extra_info": null
    },
    {
      "timestamp": "2025-04-25T14:38:21.834613Z",
      "status": "UP",
      "response_time": 0.276,
      "extra_info": null
    },
    {
      "timestamp": "2025-04-25T14:48:51.464121Z",
      "status": "UP",
      "response_time": 0.335,
      "extra_info": null
    },
    {
      "timestamp": "2025-04-25T14:58:49.172867Z",
      "status": "UP",
      "response_time": 0.412,
      "extra_info": null
    },
    {
      "timestamp": "2025-04-25T15:26:22.295605Z",
      "status": "UP",
      "response_time": 0.123,
      "extra_info": null
    },
    {
      "timestamp": "2025-04-25T15:41:15.282203Z",
      "status": "UP",
      "response_time": 0.376,
      "extra_info": null
    },
    {
      "timestamp": "2025-04-25T15:51:04.375331Z",
      "status": "UP",
      "response_time": 0.414,
      "extra_info": null
    }
  ]
}