{
  "status": "UP",
  "response_time": 0.40729308128356934,
  "extra_info": null,
  "stable_count": 797,
  "degraded_count": 0,
  "alert_mode": false,
  "last_check_timestamp_utc": "2025-10-24T21:53:43.931735Z",
  "recent_response_times": [
    0.4192821979522705,
    0.34346818923950195,
    0.40729308128356934
  ],
  "history": [
    {
      "timestamp": "2025-10-24T07:46:54.755073Z",
      "status": "UP",
      "response_time": 0.273,
      "extra_info": null
    },
    {
      "timestamp": "2025-10-24T07:56:24.937352Z",
      "status": "UP",
      "response_time": 0.308,
      "extra_info": null
    },
    {
      "timestamp": "2025-10-24T08:27:52.311491Z",
      "status": "UP",
      "response_time": 0.344,
      "extra_info": null
    },
    {
      "timestamp": "2025-10-24T08:48:19.681356Z",
      "status": "UP",
      "response_time": 0.424,
      "extra_info": null
    },
    {
      "timestamp": "2025-10-24T08:58:36.382063Z",
      "status": "UP",
      "response_time": 0.363,
      "extra_info": null
    },
    {
      "timestamp": "2025-10-24T09:27:47.096332Z",
      "status": "UP",
      "response_time": 0.304,
      "extra_info": null
    },
    {
      "timestamp": "2025-10-24T09:41:46.249756Z",
      "status": "UP",
      "response_time": 0.361,
      "extra_info": null
    },
    {
      "timestamp": "2025-10-24T09:51:38.494155Z",
      "status": "UP",
      "response_time": 0.283,
      "extra_info": null
    },
    {
      "timestamp": "2025-10-24T10:11:15.868687Z",
      "status": "UP",
      "response_time": 0.174,
      "extra_info": null
    },
    {
      "timestamp": "2025-10-24T10:36:16.863036Z",
      "status": "UP",
      "response_time": 0.23,
      "extra_info": null
    },
    {
      "timestamp": "2025-10-24T10:49:03.158567Z",
      "status": "UP",
      "response_time": 0.195,
      "extra_info": null
    },
    {
      "timestamp": "2025-10-24T10:59:11.044528Z",
      "status": "UP",
      "response_time": 0.309,
      "extra_info": null
    },
    {
      "timestamp": "2025-10-24T11:22:35.874089Z",
      "status": "UP",
      "response_time": 0.441,
      "extra_info": null
    },
    {
      "timestamp": "2025-10-24T11:35:25.357281Z",
      "status": "UP",
      "response_time": 0.249,
      "extra_info": null
    },
    {
      "timestamp": "2025-10-24T11:44:57.082563Z",
      "status": "UP",
      "response_time": 0.41,
      "extra_info": null
    },
    {
      "timestamp": "2025-10-24T11:54:41.909664Z",
      "status": "UP",
      "response_time": 0.26,
      "extra_info": null
    },
    {
      "timestamp": "2025-10-24T12:36:16.578703Z",
      "status": "UP",
      "response_time": 0.245,
      "extra_info": null
    },
    {
      "timestamp": "2025-10-24T13:17:26.158003Z",
      "status": "UP",
      "response_time": 0.294,
      "extra_info": null
    },
    {
      "timestamp": "2025-10-24T13:43:48.781188Z",
      "status": "UP",
      "response_time": 0.332,
      "extra_info": null
    },
    {
      "timestamp": "2025-10-24T13:53:42.811365Z",
      "status": "UP",
      "response_time": 0.353,
      "extra_info": null
    },
    {
      "timestamp": "2025-10-24T14:14:44.465431Z",
      "status": "UP",
      "response_time": 0.406,
      "extra_info": null
    },
    {
      "timestamp": "2025-10-24T14:37:35.636079Z",
      "status": "UP",
      "response_time": 0.255,
      "extra_info": null
    },
    {
      "timestamp": "2025-10-24T14:51:08.325625Z",
      "status": "UP",
      "response_time": 0.313,
      "extra_info": null
    },
    {
      "timestamp": "2025-10-24T15:09:20.423952Z",
      "status": "UP",
      "response_time": 0.357,
      "extra_info": null
    },
    {
      "timestamp": "2025-10-24T15:31:36.969865Z",
      "status": "UP",
      "response_time": 0.347,
      "extra_info": null
    },
    {
      "timestamp": "2025-10-24T15:44:47.716575Z",
      "status": "UP",
      "response_time": 0.311,
      "extra_info": null
    },
    {
      "timestamp": "2025-10-24T15:54:52.373605Z",
      "status": "UP",
      "response_time": 0.387,
      "extra_info": null
    },
    {
      "timestamp": "2025-10-24T16:20:54.434132Z",
      "status": "UP",
      "response_time": 0.126,
      "extra_info": null
    },
    {
      "timestamp": "2025-10-24T16:43:16.428747Z",
      "status": "UP",
      "response_time": 0.232,
      "extra_info": null
    },
    {
      "timestamp": "2025-10-24T16:55:31.627300Z",
      "status": "UP",
      "response_time": 0.396,
      "extra_info": null
    },
    {
      "timestamp": "2025-10-24T17:16:25.276785Z",
      "status": "UP",
      "response_time": 0.386,
      "extra_info": null
    },
    {
      "timestamp": "2025-10-24T17:32:37.328656Z",
      "status": "UP",
      "response_time": 0.238,
      "extra_info": null
    },
    {
      "timestamp": "2025-10-24T17:43:36.914940Z",
      "status": "UP",
      "response_time": 0.345,
      "extra_info": null
    },
    {
      "timestamp": "2025-10-24T17:53:22.106876Z",
      "status": "UP",
      "response_time": 0.293,
      "extra_info": null
    },
    {
      "timestamp": "2025-10-24T18:19:29.521827Z",
      "status": "UP",
      "response_time": 0.326,
      "extra_info": null
    },
    {
      "timestamp": "2025-10-24T18:43:00.954759Z",
      "status": "UP",
      "response_time": 0.133,
      "extra_info": null
    },
    {
      "timestamp": "2025-10-24T18:54:03.301440Z",
      "status": "UP",
      "response_time": 0.126,
      "extra_info": null
    },
    {
      "timestamp": "2025-10-24T19:12:20.172084Z",
      "status": "UP",
      "response_time": 0.608,
      "extra_info": null
    },
    {
      "timestamp": "2025-10-24T19:26:15.468695Z",
      "status": "UP",
      "response_time": 0.152,
      "extra_info": null
    },
    {
      "timestamp": "2025-10-24T19:37:48.278640Z",
      "status": "UP",
      "response_time": 0.312,
      "extra_info": null
    },
    {
      "timestamp": "2025-10-24T19:47:44.695906Z",
      "status": "UP",
      "response_time": 0.258,
      "extra_info": null
    },
    {
      "timestamp": "2025-10-24T19:57:19.910368Z",
      "status": "UP",
      "response_time": 0.28,
      "extra_info": null
    },
    {
      "timestamp": "2025-10-24T20:25:15.001748Z",
      "status": "UP",
      "response_time": 0.414,
      "extra_info": null
    },
    {
      "timestamp": "2025-10-24T20:40:32.525214Z",
      "status": "UP",
      "response_time": 0.345,
      "extra_info": null
    },
    {
      "timestamp": "2025-10-24T20:50:22.979607Z",
      "status": "UP",
      "response_time": 0.245,
      "extra_info": null
    },
    {
      "timestamp": "2025-10-24T21:00:00.524478Z",
      "status": "UP",
      "response_time": 0.267,
      "extra_info": null
    },
    {
      "timestamp": "2025-10-24T21:22:58.294687Z",
      "status": "UP",
      "response_time": 0.304,
      "extra_info": null
    },
    {
      "timestamp": "2025-10-24T21:34:34.643860Z",
      "status": "UP",
      "response_time": 0.419,
      "extra_info": null
    },
    {
      "timestamp": "2025-10-24T21:44:13.746397Z",
      "status": "UP",
      "response_time": 0.343,
      "extra_info": null
    },
    {
      "timestamp": "2025-10-24T21:53:43.931735Z",
      "status": "UP",
      "response_time": 0.407,
      "extra_info": null
    }
  ]
}