{
  "status": "UP",
  "response_time": 0.24024629592895508,
  "extra_info": null,
  "stable_count": 5369,
  "degraded_count": 0,
  "alert_mode": false,
  "last_check_timestamp_utc": "2026-01-28T00:42:22.862876Z",
  "recent_response_times": [
    0.14963054656982422,
    0.32419490814208984,
    0.24024629592895508
  ],
  "history": [
    {
      "timestamp": "2026-01-27T13:24:51.104950Z",
      "status": "UP",
      "response_time": 0.241,
      "extra_info": null
    },
    {
      "timestamp": "2026-01-27T13:46:10.561657Z",
      "status": "UP",
      "response_time": 0.206,
      "extra_info": null
    },
    {
      "timestamp": "2026-01-27T14:02:10.695870Z",
      "status": "UP",
      "response_time": 0.342,
      "extra_info": null
    },
    {
      "timestamp": "2026-01-27T14:17:37.247127Z",
      "status": "UP",
      "response_time": 0.34,
      "extra_info": null
    },
    {
      "timestamp": "2026-01-27T14:34:26.304391Z",
      "status": "UP",
      "response_time": 0.234,
      "extra_info": null
    },
    {
      "timestamp": "2026-01-27T14:53:01.292658Z",
      "status": "UP",
      "response_time": 0.133,
      "extra_info": null
    },
    {
      "timestamp": "2026-01-27T15:04:12.690490Z",
      "status": "UP",
      "response_time": 0.245,
      "extra_info": null
    },
    {
      "timestamp": "2026-01-27T15:17:46.177280Z",
      "status": "UP",
      "response_time": 0.42,
      "extra_info": null
    },
    {
      "timestamp": "2026-01-27T15:34:41.687381Z",
      "status": "UP",
      "response_time": 0.304,
      "extra_info": null
    },
    {
      "timestamp": "2026-01-27T15:48:41.589346Z",
      "status": "UP",
      "response_time": 0.306,
      "extra_info": null
    },
    {
      "timestamp": "2026-01-27T15:58:18.838226Z",
      "status": "UP",
      "response_time": 0.285,
      "extra_info": null
    },
    {
      "timestamp": "2026-01-27T16:12:50.980090Z",
      "status": "UP",
      "response_time": 0.204,
      "extra_info": null
    },
    {
      "timestamp": "2026-01-27T16:28:35.638122Z",
      "status": "UP",
      "response_time": 0.138,
      "extra_info": null
    },
    {
      "timestamp": "2026-01-27T16:46:28.102569Z",
      "status": "UP",
      "response_time": 0.144,
      "extra_info": null
    },
    {
      "timestamp": "2026-01-27T17:00:04.033127Z",
      "status": "UP",
      "response_time": 0.331,
      "extra_info": null
    },
    {
      "timestamp": "2026-01-27T17:14:50.334250Z",
      "status": "UP",
      "response_time": 0.28,
      "extra_info": null
    },
    {
      "timestamp": "2026-01-27T17:30:17.876755Z",
      "status": "UP",
      "response_time": 0.352,
      "extra_info": null
    },
    {
      "timestamp": "2026-01-27T17:45:43.697368Z",
      "status": "UP",
      "response_time": 0.336,
      "extra_info": null
    },
    {
      "timestamp": "2026-01-27T17:57:00.499797Z",
      "status": "UP",
      "response_time": 0.388,
      "extra_info": null
    },
    {
      "timestamp": "2026-01-27T18:15:22.705672Z",
      "status": "UP",
      "response_time": 0.218,
      "extra_info": null
    },
    {
      "timestamp": "2026-01-27T18:32:55.103867Z",
      "status": "UP",
      "response_time": 0.138,
      "extra_info": null
    },
    {
      "timestamp": "2026-01-27T18:54:24.333342Z",
      "status": "UP",
      "response_time": 0.354,
      "extra_info": null
    },
    {
      "timestamp": "2026-01-27T19:09:10.006017Z",
      "status": "UP",
      "response_time": 0.335,
      "extra_info": null
    },
    {
      "timestamp": "2026-01-27T19:23:15.624929Z",
      "status": "UP",
      "response_time": 0.121,
      "extra_info": null
    },
    {
      "timestamp": "2026-01-27T19:37:33.243014Z",
      "status": "UP",
      "response_time": 0.279,
      "extra_info": null
    },
    {
      "timestamp": "2026-01-27T19:48:55.004301Z",
      "status": "UP",
      "response_time": 0.367,
      "extra_info": null
    },
    {
      "timestamp": "2026-01-27T19:57:32.229963Z",
      "status": "UP",
      "response_time": 0.318,
      "extra_info": null
    },
    {
      "timestamp": "2026-01-27T20:09:59.274246Z",
      "status": "UP",
      "response_time": 0.403,
      "extra_info": null
    },
    {
      "timestamp": "2026-01-27T20:23:39.707724Z",
      "status": "UP",
      "response_time": 0.301,
      "extra_info": null
    },
    {
      "timestamp": "2026-01-27T20:37:20.696260Z",
      "status": "UP",
      "response_time": 0.242,
      "extra_info": null
    },
    {
      "timestamp": "2026-01-27T20:48:32.015779Z",
      "status": "UP",
      "response_time": 0.198,
      "extra_info": null
    },
    {
      "timestamp": "2026-01-27T20:57:51.295972Z",
      "status": "UP",
      "response_time": 0.277,
      "extra_info": null
    },
    {
      "timestamp": "2026-01-27T21:07:48.057362Z",
      "status": "UP",
      "response_time": 0.286,
      "extra_info": null
    },
    {
      "timestamp": "2026-01-27T21:20:40.774292Z",
      "status": "UP",
      "response_time": 0.457,
      "extra_info": null
    },
    {
      "timestamp": "2026-01-27T21:32:21.703841Z",
      "status": "UP",
      "response_time": 0.169,
      "extra_info": null
    },
    {
      "timestamp": "2026-01-27T21:42:14.306248Z",
      "status": "UP",
      "response_time": 0.125,
      "extra_info": null
    },
    {
      "timestamp": "2026-01-27T21:51:17.312947Z",
      "status": "UP",
      "response_time": 0.228,
      "extra_info": null
    },
    {
      "timestamp": "2026-01-27T21:58:49.394430Z",
      "status": "UP",
      "response_time": 0.374,
      "extra_info": null
    },
    {
      "timestamp": "2026-01-27T22:10:19.176953Z",
      "status": "UP",
      "response_time": 0.417,
      "extra_info": null
    },
    {
      "timestamp": "2026-01-27T22:24:02.381688Z",
      "status": "UP",
      "response_time": 0.262,
      "extra_info": null
    },
    {
      "timestamp": "2026-01-27T22:37:38.145281Z",
      "status": "UP",
      "response_time": 0.351,
      "extra_info": null
    },
    {
      "timestamp": "2026-01-27T22:48:20.158851Z",
      "status": "UP",
      "response_time": 0.143,
      "extra_info": null
    },
    {
      "timestamp": "2026-01-27T22:56:55.997254Z",
      "status": "UP",
      "response_time": 0.246,
      "extra_info": null
    },
    {
      "timestamp": "2026-01-27T23:09:05.727218Z",
      "status": "UP",
      "response_time": 0.396,
      "extra_info": null
    },
    {
      "timestamp": "2026-01-27T23:22:15.967479Z",
      "status": "UP",
      "response_time": 0.212,
      "extra_info": null
    },
    {
      "timestamp": "2026-01-27T23:34:24.613409Z",
      "status": "UP",
      "response_time": 0.139,
      "extra_info": null
    },
    {
      "timestamp": "2026-01-27T23:44:58.522978Z",
      "status": "UP",
      "response_time": 0.286,
      "extra_info": null
    },
    {
      "timestamp": "2026-01-27T23:53:47.526425Z",
      "status": "UP",
      "response_time": 0.15,
      "extra_info": null
    },
    {
      "timestamp": "2026-01-28T00:09:32.655896Z",
      "status": "UP",
      "response_time": 0.324,
      "extra_info": null
    },
    {
      "timestamp": "2026-01-28T00:42:22.862876Z",
      "status": "UP",
      "response_time": 0.24,
      "extra_info": null
    }
  ]
}