{
  "status": "UP",
  "response_time": 0.427581787109375,
  "extra_info": null,
  "stable_count": 555,
  "degraded_count": 0,
  "alert_mode": false,
  "last_check_timestamp_utc": "2025-11-30T04:51:45.236517Z",
  "recent_response_times": [
    0.3129696846008301,
    0.14186573028564453,
    0.427581787109375
  ],
  "history": [
    {
      "timestamp": "2025-11-29T17:44:14.428027Z",
      "status": "UP",
      "response_time": 0.293,
      "extra_info": null
    },
    {
      "timestamp": "2025-11-29T17:51:51.289838Z",
      "status": "UP",
      "response_time": 0.366,
      "extra_info": null
    },
    {
      "timestamp": "2025-11-29T17:59:14.009330Z",
      "status": "UP",
      "response_time": 0.196,
      "extra_info": null
    },
    {
      "timestamp": "2025-11-29T18:10:55.008953Z",
      "status": "UP",
      "response_time": 0.328,
      "extra_info": null
    },
    {
      "timestamp": "2025-11-29T18:25:24.728610Z",
      "status": "UP",
      "response_time": 0.327,
      "extra_info": null
    },
    {
      "timestamp": "2025-11-29T18:40:12.060841Z",
      "status": "UP",
      "response_time": 0.331,
      "extra_info": null
    },
    {
      "timestamp": "2025-11-29T18:50:23.372218Z",
      "status": "UP",
      "response_time": 0.245,
      "extra_info": null
    },
    {
      "timestamp": "2025-11-29T18:57:44.957574Z",
      "status": "UP",
      "response_time": 0.363,
      "extra_info": null
    },
    {
      "timestamp": "2025-11-29T19:07:22.217346Z",
      "status": "UP",
      "response_time": 0.26,
      "extra_info": null
    },
    {
      "timestamp": "2025-11-29T19:18:45.814214Z",
      "status": "UP",
      "response_time": 0.205,
      "extra_info": null
    },
    {
      "timestamp": "2025-11-29T19:27:13.502742Z",
      "status": "UP",
      "response_time": 0.193,
      "extra_info": null
    },
    {
      "timestamp": "2025-11-29T19:35:36.710091Z",
      "status": "UP",
      "response_time": 0.359,
      "extra_info": null
    },
    {
      "timestamp": "2025-11-29T19:42:57.172957Z",
      "status": "UP",
      "response_time": 0.489,
      "extra_info": null
    },
    {
      "timestamp": "2025-11-29T19:50:20.471593Z",
      "status": "UP",
      "response_time": 0.38,
      "extra_info": null
    },
    {
      "timestamp": "2025-11-29T19:57:45.684328Z",
      "status": "UP",
      "response_time": 0.378,
      "extra_info": null
    },
    {
      "timestamp": "2025-11-29T20:08:59.224573Z",
      "status": "UP",
      "response_time": 0.344,
      "extra_info": null
    },
    {
      "timestamp": "2025-11-29T20:22:04.217505Z",
      "status": "UP",
      "response_time": 0.403,
      "extra_info": null
    },
    {
      "timestamp": "2025-11-29T20:33:19.928402Z",
      "status": "UP",
      "response_time": 0.405,
      "extra_info": null
    },
    {
      "timestamp": "2025-11-29T20:42:27.993510Z",
      "status": "UP",
      "response_time": 0.311,
      "extra_info": null
    },
    {
      "timestamp": "2025-11-29T20:50:17.390659Z",
      "status": "UP",
      "response_time": 0.428,
      "extra_info": null
    },
    {
      "timestamp": "2025-11-29T20:57:58.532472Z",
      "status": "UP",
      "response_time": 0.34,
      "extra_info": null
    },
    {
      "timestamp": "2025-11-29T21:08:10.947778Z",
      "status": "UP",
      "response_time": 0.137,
      "extra_info": null
    },
    {
      "timestamp": "2025-11-29T21:20:11.322316Z",
      "status": "UP",
      "response_time": 0.268,
      "extra_info": null
    },
    {
      "timestamp": "2025-11-29T21:29:53.945789Z",
      "status": "UP",
      "response_time": 0.447,
      "extra_info": null
    },
    {
      "timestamp": "2025-11-29T21:38:32.489481Z",
      "status": "UP",
      "response_time": 0.449,
      "extra_info": null
    },
    {
      "timestamp": "2025-11-29T21:46:08.380832Z",
      "status": "UP",
      "response_time": 0.138,
      "extra_info": null
    },
    {
      "timestamp": "2025-11-29T21:53:49.070800Z",
      "status": "UP",
      "response_time": 0.128,
      "extra_info": null
    },
    {
      "timestamp": "2025-11-29T22:02:20.272176Z",
      "status": "UP",
      "response_time": 0.171,
      "extra_info": null
    },
    {
      "timestamp": "2025-11-29T22:13:20.012000Z",
      "status": "UP",
      "response_time": 0.25,
      "extra_info": null
    },
    {
      "timestamp": "2025-11-29T22:26:41.205279Z",
      "status": "UP",
      "response_time": 0.213,
      "extra_info": null
    },
    {
      "timestamp": "2025-11-29T22:37:00.655492Z",
      "status": "UP",
      "response_time": 0.344,
      "extra_info": null
    },
    {
      "timestamp": "2025-11-29T22:45:05.524458Z",
      "status": "UP",
      "response_time": 0.349,
      "extra_info": null
    },
    {
      "timestamp": "2025-11-29T22:52:24.794670Z",
      "status": "UP",
      "response_time": 0.389,
      "extra_info": null
    },
    {
      "timestamp": "2025-11-29T23:00:04.112690Z",
      "status": "UP",
      "response_time": 0.276,
      "extra_info": null
    },
    {
      "timestamp": "2025-11-29T23:10:50.111644Z",
      "status": "UP",
      "response_time": 0.265,
      "extra_info": null
    },
    {
      "timestamp": "2025-11-29T23:23:45.380253Z",
      "status": "UP",
      "response_time": 0.251,
      "extra_info": null
    },
    {
      "timestamp": "2025-11-29T23:32:16.858007Z",
      "status": "UP",
      "response_time": 0.334,
      "extra_info": null
    },
    {
      "timestamp": "2025-11-29T23:40:51.111668Z",
      "status": "UP",
      "response_time": 0.312,
      "extra_info": null
    },
    {
      "timestamp": "2025-11-29T23:48:28.296440Z",
      "status": "UP",
      "response_time": 0.267,
      "extra_info": null
    },
    {
      "timestamp": "2025-11-29T23:55:45.059485Z",
      "status": "UP",
      "response_time": 0.138,
      "extra_info": null
    },
    {
      "timestamp": "2025-11-30T00:29:42.590207Z",
      "status": "UP",
      "response_time": 0.404,
      "extra_info": null
    },
    {
      "timestamp": "2025-11-30T00:55:25.300842Z",
      "status": "UP",
      "response_time": 0.374,
      "extra_info": null
    },
    {
      "timestamp": "2025-11-30T01:33:56.506633Z",
      "status": "UP",
      "response_time": 0.389,
      "extra_info": null
    },
    {
      "timestamp": "2025-11-30T02:26:13.500693Z",
      "status": "UP",
      "response_time": 0.277,
      "extra_info": null
    },
    {
      "timestamp": "2025-11-30T03:06:09.535517Z",
      "status": "UP",
      "response_time": 0.206,
      "extra_info": null
    },
    {
      "timestamp": "2025-11-30T03:41:49.506714Z",
      "status": "UP",
      "response_time": 0.25,
      "extra_info": null
    },
    {
      "timestamp": "2025-11-30T04:04:03.914588Z",
      "status": "UP",
      "response_time": 0.377,
      "extra_info": null
    },
    {
      "timestamp": "2025-11-30T04:20:52.669482Z",
      "status": "UP",
      "response_time": 0.313,
      "extra_info": null
    },
    {
      "timestamp": "2025-11-30T04:38:25.871094Z",
      "status": "UP",
      "response_time": 0.142,
      "extra_info": null
    },
    {
      "timestamp": "2025-11-30T04:51:45.236517Z",
      "status": "UP",
      "response_time": 0.428,
      "extra_info": null
    }
  ]
}