{
  "status": "UP",
  "response_time": 0.21548843383789062,
  "extra_info": null,
  "stable_count": 7919,
  "degraded_count": 0,
  "alert_mode": false,
  "last_check_timestamp_utc": "2026-03-05T18:12:14.976600Z",
  "recent_response_times": [
    0.32750582695007324,
    0.24515962600708008,
    0.21548843383789062
  ],
  "history": [
    {
      "timestamp": "2026-03-04T21:50:44.523830Z",
      "status": "UP",
      "response_time": 0.349,
      "extra_info": null
    },
    {
      "timestamp": "2026-03-04T22:02:02.387315Z",
      "status": "UP",
      "response_time": 0.308,
      "extra_info": null
    },
    {
      "timestamp": "2026-03-04T22:15:48.735954Z",
      "status": "UP",
      "response_time": 0.236,
      "extra_info": null
    },
    {
      "timestamp": "2026-03-04T22:32:16.467251Z",
      "status": "UP",
      "response_time": 0.249,
      "extra_info": null
    },
    {
      "timestamp": "2026-03-04T22:49:49.805700Z",
      "status": "UP",
      "response_time": 0.291,
      "extra_info": null
    },
    {
      "timestamp": "2026-03-04T23:01:54.213743Z",
      "status": "UP",
      "response_time": 0.348,
      "extra_info": null
    },
    {
      "timestamp": "2026-03-04T23:16:06.672446Z",
      "status": "UP",
      "response_time": 0.318,
      "extra_info": null
    },
    {
      "timestamp": "2026-03-04T23:32:32.131626Z",
      "status": "UP",
      "response_time": 0.432,
      "extra_info": null
    },
    {
      "timestamp": "2026-03-04T23:47:02.828087Z",
      "status": "UP",
      "response_time": 0.391,
      "extra_info": null
    },
    {
      "timestamp": "2026-03-04T23:57:55.961955Z",
      "status": "UP",
      "response_time": 0.324,
      "extra_info": null
    },
    {
      "timestamp": "2026-03-05T00:47:34.371447Z",
      "status": "UP",
      "response_time": 0.323,
      "extra_info": null
    },
    {
      "timestamp": "2026-03-05T01:21:41.919735Z",
      "status": "UP",
      "response_time": 0.326,
      "extra_info": null
    },
    {
      "timestamp": "2026-03-05T02:10:57.067739Z",
      "status": "UP",
      "response_time": 0.289,
      "extra_info": null
    },
    {
      "timestamp": "2026-03-05T03:11:53.438539Z",
      "status": "UP",
      "response_time": 0.211,
      "extra_info": null
    },
    {
      "timestamp": "2026-03-05T03:58:56.107280Z",
      "status": "UP",
      "response_time": 0.226,
      "extra_info": null
    },
    {
      "timestamp": "2026-03-05T04:40:26.033007Z",
      "status": "UP",
      "response_time": 0.129,
      "extra_info": null
    },
    {
      "timestamp": "2026-03-05T05:10:00.771806Z",
      "status": "UP",
      "response_time": 0.236,
      "extra_info": null
    },
    {
      "timestamp": "2026-03-05T05:35:02.219150Z",
      "status": "UP",
      "response_time": 0.32,
      "extra_info": null
    },
    {
      "timestamp": "2026-03-05T05:58:09.394082Z",
      "status": "UP",
      "response_time": 0.449,
      "extra_info": null
    },
    {
      "timestamp": "2026-03-05T06:26:18.132301Z",
      "status": "UP",
      "response_time": 0.424,
      "extra_info": null
    },
    {
      "timestamp": "2026-03-05T06:48:25.524891Z",
      "status": "UP",
      "response_time": 0.264,
      "extra_info": null
    },
    {
      "timestamp": "2026-03-05T07:11:30.782857Z",
      "status": "UP",
      "response_time": 0.381,
      "extra_info": null
    },
    {
      "timestamp": "2026-03-05T07:31:36.629482Z",
      "status": "UP",
      "response_time": 0.169,
      "extra_info": null
    },
    {
      "timestamp": "2026-03-05T07:51:13.309322Z",
      "status": "UP",
      "response_time": 0.336,
      "extra_info": null
    },
    {
      "timestamp": "2026-03-05T08:04:26.072898Z",
      "status": "UP",
      "response_time": 0.301,
      "extra_info": null
    },
    {
      "timestamp": "2026-03-05T08:21:46.540633Z",
      "status": "UP",
      "response_time": 0.366,
      "extra_info": null
    },
    {
      "timestamp": "2026-03-05T08:41:24.898026Z",
      "status": "UP",
      "response_time": 0.182,
      "extra_info": null
    },
    {
      "timestamp": "2026-03-05T09:01:43.351807Z",
      "status": "UP",
      "response_time": 0.231,
      "extra_info": null
    },
    {
      "timestamp": "2026-03-05T09:23:14.649771Z",
      "status": "UP",
      "response_time": 0.344,
      "extra_info": null
    },
    {
      "timestamp": "2026-03-05T09:43:28.613527Z",
      "status": "UP",
      "response_time": 0.292,
      "extra_info": null
    },
    {
      "timestamp": "2026-03-05T10:03:10.443353Z",
      "status": "UP",
      "response_time": 0.35,
      "extra_info": null
    },
    {
      "timestamp": "2026-03-05T10:22:28.854962Z",
      "status": "UP",
      "response_time": 0.408,
      "extra_info": null
    },
    {
      "timestamp": "2026-03-05T10:41:47.624187Z",
      "status": "UP",
      "response_time": 0.197,
      "extra_info": null
    },
    {
      "timestamp": "2026-03-05T11:02:26.727733Z",
      "status": "UP",
      "response_time": 0.205,
      "extra_info": null
    },
    {
      "timestamp": "2026-03-05T11:20:08.777390Z",
      "status": "UP",
      "response_time": 0.245,
      "extra_info": null
    },
    {
      "timestamp": "2026-03-05T11:37:58.977316Z",
      "status": "UP",
      "response_time": 0.309,
      "extra_info": null
    },
    {
      "timestamp": "2026-03-05T11:52:30.623707Z",
      "status": "UP",
      "response_time": 0.274,
      "extra_info": null
    },
    {
      "timestamp": "2026-03-05T12:03:05.752416Z",
      "status": "UP",
      "response_time": 0.305,
      "extra_info": null
    },
    {
      "timestamp": "2026-03-05T12:25:21.080035Z",
      "status": "UP",
      "response_time": 0.254,
      "extra_info": null
    },
    {
      "timestamp": "2026-03-05T12:47:53.279316Z",
      "status": "UP",
      "response_time": 0.294,
      "extra_info": null
    },
    {
      "timestamp": "2026-03-05T13:19:11.878041Z",
      "status": "UP",
      "response_time": 0.357,
      "extra_info": null
    },
    {
      "timestamp": "2026-03-05T13:46:43.363459Z",
      "status": "UP",
      "response_time": 0.331,
      "extra_info": null
    },
    {
      "timestamp": "2026-03-05T14:08:05.930994Z",
      "status": "UP",
      "response_time": 0.341,
      "extra_info": null
    },
    {
      "timestamp": "2026-03-05T14:29:14.720287Z",
      "status": "UP",
      "response_time": 0.253,
      "extra_info": null
    },
    {
      "timestamp": "2026-03-05T14:51:41.509150Z",
      "status": "UP",
      "response_time": 0.358,
      "extra_info": null
    },
    {
      "timestamp": "2026-03-05T15:11:26.686689Z",
      "status": "UP",
      "response_time": 0.375,
      "extra_info": null
    },
    {
      "timestamp": "2026-03-05T15:34:18.887702Z",
      "status": "UP",
      "response_time": 0.167,
      "extra_info": null
    },
    {
      "timestamp": "2026-03-05T15:57:32.095595Z",
      "status": "UP",
      "response_time": 0.328,
      "extra_info": null
    },
    {
      "timestamp": "2026-03-05T17:24:13.034042Z",
      "status": "UP",
      "response_time": 0.245,
      "extra_info": null
    },
    {
      "timestamp": "2026-03-05T18:12:14.976600Z",
      "status": "UP",
      "response_time": 0.215,
      "extra_info": null
    }
  ]
}